backupper/__init__.py
backupper/__main__.py
backupper/cli.py
backupper/utils.py
backupper/connect/__init__.py
backupper/connect/dummystorage.py
backupper/connect/ftpstorage.py
backupper/connect/utils.py
backupper-0.3a3.dist-info/DESCRIPTION.rst
backupper-0.3a3.dist-info/METADATA
backupper-0.3a3.dist-info/RECORD
backupper-0.3a3.dist-info/WHEEL
backupper-0.3a3.dist-info/entry_points.txt
backupper-0.3a3.dist-info/metadata.json
backupper-0.3a3.dist-info/top_level.txt
