Metadata-Version: 2.0
Name: backupper
Version: 0.3a3
Summary: Easy and configurable backup tool
Home-page: https://github.com/dolfinsbizou/backupper
Author: Guillaume Jorandon
Author-email: jorandon@gmail.com
License: MIT
Platform: UNKNOWN
Classifier: Development Status :: 3 - Alpha
Classifier: Environment :: Console
Classifier: Intended Audience :: System Administrators
Classifier: Natural Language :: English
Classifier: Programming Language :: Python :: 3.5
Classifier: Programming Language :: Python :: 3 :: Only
Classifier: Operating System :: OS Independent
Classifier: License :: OSI Approved :: MIT License
Classifier: Topic :: System :: Archiving :: Backup
Requires-Dist: python-gnupg
Requires-Dist: pyyaml
